autoproxy/__init__.py
autoproxy/__utils.py
autoproxy/sources.py
autoproxy-0.0.2.dist-info/LICENSES.txt
autoproxy-0.0.2.dist-info/METADATA
autoproxy-0.0.2.dist-info/WHEEL
autoproxy-0.0.2.dist-info/top_level.txt
autoproxy-0.0.2.dist-info/RECORD
