Metadata-Version: 2.1
Name: autoproxy
Version: 0.0.2
Summary: This package give you auto proxies for your projects 
Home-page: UNKNOWN
Author: 01270
Author-email: <mail@noemail.com>
License: UNKNOWN
Keywords: proxy,auto proxy,proxy scrapper
Platform: UNKNOWN
Classifier: Development Status :: 1 - Planning
Classifier: Intended Audience :: Developers
Classifier: Programming Language :: Python :: 3
Classifier: Operating System :: Unix
Classifier: Operating System :: MacOS :: MacOS X
Classifier: Operating System :: Microsoft :: Windows
License-File: LICENSES.txt
Requires-Dist: aiohttp
